{
    "Records": [
        {
            "body": "{\"is_get\":true,\"event\":{\"version\":\"2.0\",\"routeKey\":\"GET /efsdv1\",\"rawPath\":\"/efsdv1\",\"rawQueryString\":\"sub1=IwZXh0bgNhZW0BMABhZGlkAasadlPq9KUBHf8VIecHByWDvwPNzqco8rpKqp73sMxEfXkDsGFykfGgby7ASB9l2FVnEw_aem_rxAkw4GAU283fxROZFDy8A%7C692c2ee4-2fa3-4077-9748-93b6f9f89bba%7Cfb%7C2a02%3Ac7c%3A53b1%3A2400%3A5085%3Aed01%3A45c5%3Abd08%7CGB&sub2=120218910544520197%7C120218910544490197%7C120218910544480197%7C1407283946754026&sub3=001_CleaningJobs_UK_EN_070125_Sedo%7C1736411160%7CEngland%7CRomford&revenue=0.2438&domain=cleaning-companies-in-london.site&txid=677f890f7ef95&cli\",\"headers\":{\"accept\":\"*/*\",\"content-length\":\"0\",\"host\":\"sftrklnk.com\",\"user-agent\":\"Sedoparking Click Postback\",\"x-amzn-trace-id\":\"Root=1-677f8a74-3414ef6938eca9482368f1e5\",\"x-forwarded-for\":\"91.195.241.6\",\"x-forwarded-port\":\"443\",\"x-forwarded-proto\":\"https\"},\"queryStringParameters\":{\"cli\":\"\",\"domain\":\"cleaning-companies-in-london.site\",\"revenue\":\"0.2438\",\"sub1\":\"IwZXh0bgNhZW0BMABhZGlkAasadlPq9KUBHf8VIecHByWDvwPNzqco8rpKqp73sMxEfXkDsGFykfGgby7ASB9l2FVnEw_aem_rxAkw4GAU283fxROZFDy8A|692c2ee4-2fa3-4077-9748-93b6f9f89bba|fb|2a02:c7c:53b1:2400:5085:ed01:45c5:bd08|GB\",\"sub2\":\"120218910544520197|120218910544490197|120218910544480197|1407283946754026\",\"sub3\":\"001_CleaningJobs_UK_EN_070125_Sedo|1736411160|England|Romford\",\"txid\":\"677f890f7ef95\"},\"requestContext\":{\"accountId\":\"033156084586\",\"apiId\":\"wqoj7agtd7\",\"domainName\":\"sftrklnk.com\",\"domainPrefix\":\"sftrklnk\",\"http\":{\"method\":\"GET\",\"path\":\"/efsdv1\",\"protocol\":\"HTTP/1.1\",\"sourceIp\":\"91.195.241.6\",\"userAgent\":\"Sedoparking Click Postback\"},\"requestId\":\"EHKSOjE_oAMEbRg=\",\"routeKey\":\"GET /efsdv1\",\"stage\":\"$default\",\"time\":\"09/Jan/2025:08:36:04 +0000\",\"timeEpoch\":1736411764215},\"isBase64Encoded\":false},\"received_at\":\"1736411764286\",\"event_network\":\"sedo\",\"is_postback\":\"1\"}"
        }
    ]
}